Metadata-Version: 1.0
Name: suchdistribution
Version: 1.0
Summary: All the things regarding Gaussian and Binomial distributions
Home-page: UNKNOWN
Author: Behan Boshoff
Author-email: bhnboshoff@gmail.com
License: UNKNOWN
Platform: UNKNOWN
